Pipeline/DPA.py
Pipeline/PAk.py
Pipeline/_DPA.cpython-37m-darwin.so
Pipeline/_PAk.cpython-37m-darwin.so
Pipeline/__init__.py
Pipeline/_template.py
Pipeline/_version.py
Pipeline/twoNN.py
Pipeline/tests/__init__.py
Pipeline/tests/test_DPA.py
Pipeline/tests/test_PAk.py
Pipeline/tests/test_common.py
Pipeline/tests/test_twoNN.py
DPA-0.0.3.dist-info/LICENSE
DPA-0.0.3.dist-info/METADATA
DPA-0.0.3.dist-info/WHEEL
DPA-0.0.3.dist-info/top_level.txt
DPA-0.0.3.dist-info/RECORD
