Metadata-Version: 2.1
Name: DPA
Version: 0.0.3
Summary: The Density Peak Advanced packages.
Home-page: UNKNOWN
Author: Maria d'Errico
License: new BSD
Platform: UNKNOWN
Classifier: Intended Audience :: Science/Research
Classifier: Intended Audience :: Developers
Classifier: License :: OSI Approved
Classifier: Programming Language :: Python
Classifier: Topic :: Software Development
Classifier: Topic :: Scientific/Engineering
Classifier: Operating System :: Microsoft :: Windows
Classifier: Operating System :: POSIX
Classifier: Operating System :: Unix
Classifier: Operating System :: MacOS
Classifier: Programming Language :: Python :: 2.7
Classifier: Programming Language :: Python :: 3.5
Classifier: Programming Language :: Python :: 3.6
Classifier: Programming Language :: Python :: 3.7
License-File: LICENSE
Requires-Dist: scikit-learn (==0.24.*)
Requires-Dist: matplotlib
Provides-Extra: docs
Requires-Dist: sphinx (==4.0.2) ; extra == 'docs'
Requires-Dist: sphinx-gallery ; extra == 'docs'
Requires-Dist: sphinx-rtd-theme ; extra == 'docs'
Requires-Dist: nbsphinx-link (==1.3.0) ; extra == 'docs'
Requires-Dist: numpydoc ; extra == 'docs'
Requires-Dist: matplotlib ; extra == 'docs'
Requires-Dist: scipy ; extra == 'docs'
Requires-Dist: jupyter ; extra == 'docs'
Requires-Dist: py-cpuinfo ; extra == 'docs'
Requires-Dist: hdbscan ; extra == 'docs'
Provides-Extra: tests
Requires-Dist: pytest ; extra == 'tests'
Requires-Dist: pytest-cov ; extra == 'tests'
Requires-Dist: pandas ; extra == 'tests'
